arianna/__init__.py
arianna/types.py
arianna/distributions/__init__.py
arianna/distributions/abstract.py
arianna/distributions/distributions.py
arianna/ppl/context.py
arianna/ppl/diagnostics.py
arianna/ppl/inference.py
arianna/ppl/shaper.py
arianna_ppl-0.3.2.dist-info/licenses/LICENSE
arianna_ppl-0.3.2.dist-info/METADATA
arianna_ppl-0.3.2.dist-info/WHEEL
arianna_ppl-0.3.2.dist-info/top_level.txt
arianna_ppl-0.3.2.dist-info/RECORD
