Metadata-Version: 2.4
Name: arianna-ppl
Version: 0.3.2
Summary: Arianna probabilistic programming language
Author-email: Arthur Lui <alui@lanl.gov>
Maintainer-email: Arthur Lui <alui@lanl.gov>
License-Expression: MIT
Project-URL: Homepage, https://github.com/lanl/arianna-ppl
Project-URL: Documentation, https://lanl.github.io/arianna-ppl
Project-URL: Repository, https://github.com/lanl/arianna-ppl
Project-URL: Issues, https://github.com/lanl/arianna-ppl/issues
Project-URL: Changelog, https://github.com/lanl/arianna-ppl/blob/master/CHANGELOG.md
Classifier: Operating System :: OS Independent
Classifier: Programming Language :: Python :: 3.10
Classifier: Programming Language :: Python :: 3.11
Classifier: Programming Language :: Python :: 3.12
Classifier: Programming Language :: Python :: 3.13
Classifier: Programming Language :: Python :: 3.14
Requires-Python: >=3.10
License-File: LICENSE
Requires-Dist: numpy>=2.2.1
Requires-Dist: pandas>=2.2.3
Requires-Dist: scipy>=1.15.0
Requires-Dist: tqdm<5.0.0,>=4.65
Dynamic: license-file
